checkword/__init__.py
checkword/main.py
checkword/processor.py
checkword-0.0.3.dist-info/METADATA
checkword-0.0.3.dist-info/WHEEL
checkword-0.0.3.dist-info/top_level.txt
checkword-0.0.3.dist-info/RECORD
