Metadata-Version: 2.1
Name: checkword
Version: 0.0.3
Summary: Package for checking text for existance of blacklisted or whitelisted words
Home-page: https://github.com/alexb007/checkword
Author: Bakhrom Rakhmonov
Author-email: alex960126@gmail.com
License: UNKNOWN
Platform: UNKNOWN
Classifier: Programming Language :: Python :: 3
Classifier: License :: OSI Approved :: MIT License
Classifier: Operating System :: OS Independent
